bencode/__init__.py
py3_bencode-0.0.3.dist-info/LICENSE
py3_bencode-0.0.3.dist-info/METADATA
py3_bencode-0.0.3.dist-info/WHEEL
py3_bencode-0.0.3.dist-info/top_level.txt
py3_bencode-0.0.3.dist-info/zip-safe
py3_bencode-0.0.3.dist-info/RECORD
