Metadata-Version: 2.1
Name: py3-bencode
Version: 0.0.3
Summary: Python 3 bencoding implementation
Home-page: https://github.com/bashkirtsevich-llc/py3bencode
Author: D.Bashkirtsevich
Author-email: bashkirtsevich@gmail.com
License: GPL3 License
Keywords: bencode rawbytes torrent bittorrent
Platform: UNKNOWN
Classifier: Programming Language :: Python
Requires-Python: >=3.6.*
